netbox_old_search/__init__.py
netbox_old_search/forms.py
netbox_old_search/middleware.py
netbox_old_search/navigation.py
netbox_old_search/search.py
netbox_old_search/urls.py
netbox_old_search/views.py
netbox_old_search/templates/netbox_old_search/search.html
netbox_old_search-1.1.0.dist-info/LICENSE
netbox_old_search-1.1.0.dist-info/METADATA
netbox_old_search-1.1.0.dist-info/WHEEL
netbox_old_search-1.1.0.dist-info/top_level.txt
netbox_old_search-1.1.0.dist-info/RECORD
