Metadata-Version: 2.2
Name: netbox-old-search
Version: 1.1.0
Summary: Brings back the old search functionality to NetBox
Home-page: https://github.com/kkthxbye-code/netbox-old-search
Author: kkthxbye-code
Author-email: festll234@gmail.com
Keywords: netbox,netbox-plugin
Classifier: Development Status :: 5 - Production/Stable
Classifier: Intended Audience :: Developers
Classifier: Natural Language :: English
Classifier: Programming Language :: Python :: 3
Classifier: Programming Language :: Python :: 3.8
Classifier: Programming Language :: Python :: 3.9
Classifier: Programming Language :: Python :: 3.10
Classifier: Programming Language :: Python :: 3.11
Requires-Python: >=3.8
License-File: LICENSE
Dynamic: author
Dynamic: author-email
Dynamic: classifier
Dynamic: description
Dynamic: description-content-type
Dynamic: home-page
Dynamic: keywords
Dynamic: requires-python
Dynamic: summary
